easydags/__init__.py
easydags/config.py
easydags/dag.py
easydags/errors.py
easydags/node.py
easydags/ops.py
easydags-0.0.2.dist-info/LICENSE
easydags-0.0.2.dist-info/METADATA
easydags-0.0.2.dist-info/WHEEL
easydags-0.0.2.dist-info/top_level.txt
easydags-0.0.2.dist-info/RECORD
