Metadata-Version: 2.1
Name: easydags
Version: 0.0.2
Summary: Dags made easy
Author: Mateo Graciano
Author-email: magralo@gmail.com
Classifier: Development Status :: 3 - Alpha
License-File: LICENSE
Requires-Dist: networkx (==2.6.3)
Requires-Dist: pydantic (==1.10)
Requires-Dist: loguru (==0.6.0)
Requires-Dist: matplotlib (==3.6.3)
Requires-Dist: pyvis (==0.3.1)
